{"title":"","uid":"f73a8e23e6f6f669cf99c7dba8fa0722","slug":"2023-02-13","date":"2023-02-13T05:11:38.429Z","updated":"2023-02-13T05:11:38.429Z","comments":true,"path":"api/articles/2023-02-13.json","keywords":null,"cover":null,"content":"","text":"","link":"","photos":[],"count_time":{"symbolsCount":0,"symbolsTime":"1 mins."},"categories":[],"tags":[],"toc":"","author":{"name":"安全书","slug":"blog-author","avatar":"https://img-blog.csdnimg.cn/20210313122054101.png","link":"/","description":"《墨守之道-Web服务安全架构与实践》","socials":{"github":"https://github.com/shengnoah","twitter":"","stackoverflow":"","wechat":"","qq":"","weibo":"https://weibo.com/u/3732639263","zhihu":"https://www.zhihu.com/people/openresty","csdn":"","juejin":"","customs":{}}},"mapped":true,"prev_post":{"title":"iCloud的文件夹的位置","uid":"e564ce5c4856dfbed477325743829e87","slug":"other/iCloud的文件夹的位置","date":"2023-02-13T05:13:56.235Z","updated":"2023-02-13T05:41:13.603Z","comments":true,"path":"api/articles/other/iCloud的文件夹的位置.json","keywords":null,"cover":null,"text":"iCloud的文件夹的位置PC的iCloud的位置。cd /Library/Mobile\\ Documents/comapple~CloudDocs 手机上Obsidian文件夹的位置。cd /Library/Mobile\\ Documents/iCloud\\md~obsidia...","link":"","photos":[],"count_time":{"symbolsCount":199,"symbolsTime":"1 mins."},"categories":[{"name":"文章","slug":"文章","count":25,"path":"api/categories/文章.json"}],"tags":[{"name":"Ruby","slug":"Ruby","count":7,"path":"api/tags/Ruby.json"}],"author":{"name":"安全书","slug":"blog-author","avatar":"https://img-blog.csdnimg.cn/20210313122054101.png","link":"/","description":"《墨守之道-Web服务安全架构与实践》","socials":{"github":"https://github.com/shengnoah","twitter":"","stackoverflow":"","wechat":"","qq":"","weibo":"https://weibo.com/u/3732639263","zhihu":"https://www.zhihu.com/people/openresty","csdn":"","juejin":"","customs":{}}}},"next_post":{"title":"<% tp.file.title %>","uid":"f3a7a1ae5810a1d115aa263fefb11fd2","slug":"templater/安书模板","date":"2023-02-13T04:58:27.063Z","updated":"2023-02-13T05:09:55.089Z","comments":true,"path":"api/articles/templater/安书模板.json","keywords":null,"cover":null,"text":"&lt;% tp.file.title %&gt;","link":"","photos":[],"count_time":{"symbolsCount":25,"symbolsTime":"1 mins."},"categories":[{"name":"文章","slug":"文章","count":25,"path":"api/categories/文章.json"}],"tags":[{"name":"Ruby","slug":"Ruby","count":7,"path":"api/tags/Ruby.json"}],"author":{"name":"安全书","slug":"blog-author","avatar":"https://img-blog.csdnimg.cn/20210313122054101.png","link":"/","description":"《墨守之道-Web服务安全架构与实践》","socials":{"github":"https://github.com/shengnoah","twitter":"","stackoverflow":"","wechat":"","qq":"","weibo":"https://weibo.com/u/3732639263","zhihu":"https://www.zhihu.com/people/openresty","csdn":"","juejin":"","customs":{}}}}}